{
    "systemMapCoord": [
        -45996.59857263771,
        0,
        -3326.3280900192362
    ],
    "systemalignment": "Hjorden",
    "metadata": {
        "skybox": "sky1.png",
        "sysdescription": "",
        "security": "Neutral",
        "exports": [],
        "focus": "",
        "intel": {},
        "development": "Unclaimed",
        "visible": true
    },
    "objects": {
        "Hearthland Gate": {
            "coordinate": [
                68333.33333333334,
                0,
                -16666.666666666668
            ],
            "type": "jumpnode",
            "jumppointtype": "Node",
            "destinations": {
                "Arrin Gate": "Hjorden"
            },
            "state": "Tethered",
            "drift": 0
        }
    },
    "sensor_relay": {},
    "terrain": {},
    "traffic": {}
}